<annotation>
	<folder>JPEGImages</folder>
	<filename>241.jpg</filename>
	<path>/content/dataset/VOC2012/JPEGImages/241.jpg</path>
	<source>
		<database>Unknown</database>
	</source>
	<size>
		<width>1536</width>
		<height>1229</height>
		<depth>3</depth>
	</size>
	<segmented>0</segmented>
	<object>
		<name>moscaDasFrutas</name>
		<pose>Unspecified</pose>
		<truncated>0</truncated>
		<difficult>0</difficult>
		<bndbox>
			<xmin>586</xmin>
			<ymin>621</ymin>
			<xmax>759</xmax>
			<ymax>847</ymax>
		</bndbox>
	</object>
</annotation>
