<annotation>
	<folder>JPEGImages</folder>
	<filename>957.jpg</filename>
	<path>/content/dataset/VOC2012/JPEGImages/957.jpg</path>
	<source>
		<database>Unknown</database>
	</source>
	<size>
		<width>552</width>
		<height>512</height>
		<depth>3</depth>
	</size>
	<segmented>0</segmented>
	<object>
		<name>moscaDasFrutas</name>
		<pose>Unspecified</pose>
		<truncated>0</truncated>
		<difficult>0</difficult>
		<bndbox>
			<xmin>61</xmin>
			<ymin>11</ymin>
			<xmax>524</xmax>
			<ymax>490</ymax>
		</bndbox>
	</object>
</annotation>
